quipucamayoc/__init__.py
quipucamayoc/aws_extract_tables.py
quipucamayoc/aws_setup.py
quipucamayoc/cli.py
quipucamayoc/old_aws_extract_tables.py
quipucamayoc/version.py
quipucamayoc-0.1.2.dist-info/LICENSE
quipucamayoc-0.1.2.dist-info/METADATA
quipucamayoc-0.1.2.dist-info/WHEEL
quipucamayoc-0.1.2.dist-info/entry_points.txt
quipucamayoc-0.1.2.dist-info/top_level.txt
quipucamayoc-0.1.2.dist-info/RECORD
