Metadata-Version: 2.1
Name: quipucamayoc
Version: 0.1.2
Summary: Tools to extract information from digitized historical documents
Home-page: https://github.com/sergiocorreia/quipucamayoc/
Author: Sergio Correia, Stephan Luck
Author-email: sergio.correia@gmail.com
License: GNU Affero General Public License v3
Keywords: ocr,data extraction,tables,economic history
Platform: UNKNOWN
Classifier: Development Status :: 3 - Alpha
Classifier: Environment :: Console
Classifier: License :: OSI Approved :: GNU Affero General Public License v3
Classifier: Programming Language :: Python :: 3 :: Only
Classifier: Programming Language :: Python :: 3.10
Classifier: Topic :: Scientific/Engineering :: Image Processing
Classifier: Operating System :: POSIX :: Linux
Classifier: Operating System :: Unix
Classifier: Operating System :: MacOS
Classifier: Operating System :: Microsoft :: Windows
Requires-Python: >=3.9
License-File: LICENSE
Requires-Dist: opencv-python (>=4.5.5.62)
Requires-Dist: numpy (>=1.21.2)
Requires-Dist: boto3 (>=1.21.1)
Requires-Dist: awscli (>=1.22.84)
Requires-Dist: click (>=8.0.3)
Requires-Dist: Pillow (>=9.0.1)
Requires-Dist: loguru (>=0.6.0)
